flake8_strftime/__init__.py
flake8_strftime/py.typed
flake8_strftime-0.3.4.dist-info/LICENSE
flake8_strftime-0.3.4.dist-info/METADATA
flake8_strftime-0.3.4.dist-info/WHEEL
flake8_strftime-0.3.4.dist-info/entry_points.txt
flake8_strftime-0.3.4.dist-info/RECORD
