Metadata-Version: 2.1
Name: flake8-strftime
Version: 0.3.4
Summary: A flake8 plugin which checks for use of platform specific strftime codes.
Author-email: Dominic Davis-Foster <dominic@davis-foster.co.uk>
License: MIT
Keywords: date,datetime,flake8,strftime,time
Home-page: https://github.com/python-formate/flake8_strftime
Project-URL: Issue Tracker, https://github.com/python-formate/flake8_strftime/issues
Project-URL: Source Code, https://github.com/python-formate/flake8_strftime
Project-URL: Documentation, https://flake8-strftime.readthedocs.io/en/latest
Platform: Windows
Platform: macOS
Platform: Linux
Classifier: Development Status :: 4 - Beta
Classifier: Framework :: Flake8
Classifier: Intended Audience :: Developers
Classifier: License :: OSI Approved :: MIT License
Classifier: Operating System :: OS Independent
Classifier: Programming Language :: Python
Classifier: Programming Language :: Python :: 3 :: Only
Classifier: Programming Language :: Python :: 3.6
Classifier: Programming Language :: Python :: 3.7
Classifier: Programming Language :: Python :: 3.8
Classifier: Programming Language :: Python :: 3.9
Classifier: Programming Language :: Python :: 3.10
Classifier: Programming Language :: Python :: 3.11
Classifier: Programming Language :: Python :: 3.12
Classifier: Programming Language :: Python :: Implementation :: CPython
Classifier: Programming Language :: Python :: Implementation :: PyPy
Classifier: Topic :: Utilities
Classifier: Typing :: Typed
Requires-Python: >=3.6
Requires-Dist: flake8>=3.7
Requires-Dist: flake8-helper>=0.1.1
